Metadata-Version: 2.2
Name: eazy
Version: 0.8.5
Summary: Pythonic photo-zs
Author-email: "G. Brammer" <gbrammer@gmail.com>
License: MIT License
Project-URL: Documentation, https://eazy-py.readthedocs.io/
Project-URL: Homepage, https://github.com/gbrammer/eazy-py
Project-URL: Source, https://github.com/gbrammer/eazy-py
Project-URL: Tracker, https://github.com/gbrammer/eazy-py/issues
Classifier: Development Status :: 3 - Alpha
Classifier: Intended Audience :: Science/Research
Classifier: Topic :: Scientific/Engineering :: Astronomy
Requires-Python: >=3.8
License-File: LICENSE.txt
Requires-Dist: astro-sedpy>=0.3
Requires-Dist: astropy
Requires-Dist: dust_extinction
Requires-Dist: h5py
Requires-Dist: matplotlib
Requires-Dist: numpy
Requires-Dist: peakutils
Requires-Dist: scipy
Requires-Dist: tqdm
Provides-Extra: docs
Requires-Dist: sphinx; extra == "docs"
Requires-Dist: sphinx-astropy; extra == "docs"
Requires-Dist: toml; extra == "docs"
Provides-Extra: test
Requires-Dist: flake8; extra == "test"
Requires-Dist: pytest>=5.1; extra == "test"
Requires-Dist: coverage; extra == "test"
Provides-Extra: vistool
Requires-Dist: dash==2.5.1; extra == "vistool"
Requires-Dist: jupyter-dash; extra == "vistool"
Requires-Dist: Werkzeug==2.0.3; extra == "vistool"
